{"title": "\u535a\u6d1b\u5c3c\u4e9a - \u4e09\u4e2a\u5b69\u5b50\u548c\u6b7b\u53bb\u7684\u6bcd\u4eb2 - \u8bc4\u8bba", "published time": "2024-03-17T15:00:00+08:00", "images": [], "content": "<div class=\"post-body entry-content\" id=\"post-body-4644031714937769843\" itemprop=\"description articleBody\">\n <div style=\"background: rgb(255, 255, 255); color: #080808; font-family: Verdana;  padding: 3px 6px;\">\n  <b style='color: black; font-family: \"Times New Roman\";'>\n   \u6765\u81ea\u535a\u6d1b\u5c3c\u4e9a\u56fd\u5bb6\u89c2\u5bdf\u5458\u7684\u5de5\u4f5c\u6b7b\u4e8e\n  </b>\n  <br style='color: black; font-family: \"Times New Roman\"; font-size: medium;'/>\n  <div class=\"gmail_default\" style='color: black; font-family: \"Times New Roman\";'>\n   <span style='color: black; font-family: \"Times New Roman\";'>\n    <br/>\n   </span>\n  </div>\n  <div class=\"gmail_default\" style='color: black; font-family: \"Times New Roman\";'>\n   <span span=\"\" style='color: black; font-family: \"Times New Roman\";'>\n    <span style='color: black; font-family: \"Times New Roman\";'>\n     \u540c\u6837\u5728\u4f5b\u7f57\u4f26\u8428\uff0c\u4e00\u4e2a\u6b7b\u53bb\u7684\u7537\u4eba\u4e8e1\u670815\u65e5\u5728\u4f69\u9c81\u5409\u4e9a\uff08Perugia\uff09\uff0c\u4e00\u540d\u7089\u5b50\u4e0a\u7684\u4e00\u6c27\u5316\u78b3\u4e00\u6c27\u5316\u78b3\uff0c\u4e00\u540d\u5987\u5973\u671d\u7740\u58c1\u7089\u5c04\u51fb\u592a\u591a\u4e86\uff0c\u5df2\u7ecf78\u5c81\u4e86\u3002 \u5b89\u5a1c\u00b7\u739b\u4e3d\u4e9a\uff08Ana Maria\uff09\u7684\u79d8\u9c81\u5c3c\u4e9a\uff08Peruviana\uff0958\u5c81\uff0c\u5f53\u5929\u5728\u7279\u91cc\u65af\u7279\uff08Trieste\uff09\uff0c\u5916\u56fd\u4eba\u4e8e1\u670824\u65e5\u5728\u516c\u5bd3\u91cc\u71c3\u70e7\u3002 1\u670828\u65e5\uff0c\u5728\u535a\u6d1b\u5c3c\u4e9a\u7f57\u9a6c\u548c\u8bfa\u74e6\u62c9\uff08Novara\n    </span>\n    <span style='color: black; font-family: \"Times New Roman\";'>\n     \u4e00\u4e2a\n    </span>\n    <span style='color: black; font-family: \"Times New Roman\";'>\n     \u7535\u7089\u548c\u7089\u5b50\u7684\u70df\u96fe\u3002 Ombretta Castellani\u53ea\u670950\u5c81\uff0c\u88ab\u5361\u8f66\u7684\u6273\u673a\u6df9\u6ca1\u4e86\u3002 \u8428\u8428\u91cc\uff08Sassari\uff09\u7684\u4e54\u74e6\u5c3c\uff08Giovanni Crimi\uff09\u4e8e2\u67084\u65e5\u56e0\u5706\u67f1\u4f53\u7684\u7206\u70b8\u800c\u53bb\u4e16\u3002 \u6211\u5728\u8fd9\u91cc\u505c\u4e0b\u6765\uff0c\u4f46\u662f\u6848\u4f8b\u7814\u7a76\u548c\u8fd9\u4e9b\u6b7b\u4ea1\u7684\u8bb0\u5f55\u662f\u65e0\u9650\u7684\uff1a\u6709\u4e9b\u4eba\u7a81\u7136\u7a81\u7136\u4ece\u5c4b\u9876\u6389\u4e0b\u6765\u6389\u4e0b\u6765\uff0c\u90a3\u4e9b\u5c06\u5934\u653e\u5728\u4eba\u5b54\u4e2d\u7684\u4eba\uff0c\u4ed6\u4eec\u5373\u5174\u7c89\u5237\u5e76\u4ece\u697c\u68af\u4e0a\u6389\u4e0b\u6765\uff0c\u4ed6\u4eec\u5f00\u59cb\u6d17\u6da4\u7a97\u6237\u7684\u7a97\u6237\u843d\u5728\u8857\u9053\u4e0a\uff0c\u90a3\u4e9b\u6210\u4e3a\u7a97\u5e18\u548c\u767e\u53f6\u7a97\u7684\u7f16\u8f91\u7684\u4eba\uff0c\u843d\u5728\u56fd\u5185\u5916\u3002 \u8c01\u5e26\u7740\u5404\u79cd\u201c\u51b0\u6c99\u201d\u56de\u5230\u8f66\u5e93\u4e2d\u7684\u52a8\u8109\uff0c\u4ed6\u4eec\u5f00\u59cb\u4fee\u526a\u82b1\u56ed\u7684\u6811\u6728\u5e76\u4e0d\u77e5\u6240\u63aa\uff0c\u7b49\u7b49\u2026\u2026\u6211\u53ef\u4ee5\u65e0\u9650\u7ee7\u7eed\u3002 \u7b80\u800c\u8a00\u4e4b\uff0c\u623f\u5b50\u5145\u6ee1\u4e86\u5371\u9669\uff0c\u8ba9\u81ea\u5df1\u505a\u9700\u8981\u8c28\u614e\u7684\u5de5\u4f5c\u975e\u5e38\u975e\u5e38\u5371\u9669\u3002 \u81ea\u4ece\u6211\u5728198\u5e74\u5b64\u72ec\u5730\u753b\u4e86\u8fd9\u5f20\u7167\u7247\u4ee5\u6765\uff0c\u4ec0\u4e48\u90fd\u6ca1\u6709\u6539\u53d8\u3002\n    </span>\n   </span>\n  </div>\n </div>\n <div style=\"clear: both;\">\n </div>\n</div>\n", "description": "\u6765\u81ea\u535a\u6d1b\u5c3c\u4e9a\u56fd\u5bb6\u89c2\u6d4b\u7ad9\u7684\u5de5\u4f5c\u4e2d\uff0c\u6b27\u6d32\u6700\u5bcc\u6709\u7684\u57ce\u5e02\u4e4b\u4e00\u5728\u6211\u7684\u535a\u6d1b\u5c3c\u4e9a\u89c9\u5f97...", "author": ["fannyhill"], "source": "https://femminismorivoluzionario.blogspot.com/2024/03/bologna-tre-bambini-e-la-madre-morta-un.html", "source_name": "femminismo proletario rivoluzionario"}