{"title": "\u00cdndia: 8 de mar\u00e7o", "published time": "2024-03-12T20:02:00+08:00", "images": [], "content": "<div class=\"post-body entry-content\" id=\"post-body-2433953609552024735\" itemprop=\"description articleBody\">\n <p>\n </p>\n <div class=\"separator\" style=\"clear: both; text-align: center;\">\n  <iframe allowfullscreen=\"allowfullscreen\" class=\"b-hbp-video b-uploaded\" frameborder=\"0\" height=\"266\" id=\"BLOGGER-video-8502d88883d81aad-15847\" mozallowfullscreen=\"mozallowfullscreen\" src=\"https://www.blogger.com/video.g?token=AD6v5dy_ADmay9EosJSQngzXx0SKD7yE5SaDf_obOxptnDVd-pjhO1w-GgLSP2V82Iacui9r811Ji6CIR2ZYS-dYHpxy6lDchQ9cj7B-Svo_Av16TCHsiajzfQ1F64fgUCMU-YD5sr4R\" webkitallowfullscreen=\"webkitallowfullscreen\" width=\"320\">\n  </iframe>\n </div>\n <br/>\n <p>\n </p>\n <div style=\"clear: both;\">\n </div>\n</div>\n", "description": "", "author": ["dazibao rojo"], "source": "https://dazibaorojo08.blogspot.com/2024/03/india-8th-of-march.html", "source_name": "Dazibao Rojo"}