{"published time": "2024-11-15T05:15:53+08:00", "images": ["https://redherald.org/wp-content/uploads/2024/11/feat-arson-barro-branco.jpg"], "content": "<div class=\"post-thumbnail\">\n <img alt=\"\" class=\"attachment-post-thumbnail size-post-thumbnail wp-post-image\" decoding=\"async\" fetchpriority=\"high\" height=\"415\" sizes=\"(max-width: 516px) 100vw, 516px\" src=\"https://redherald.org/wp-content/uploads/2024/11/feat-arson-barro-branco.jpg\" srcset=\"https://redherald.org/wp-content/uploads/2024/11/feat-arson-barro-branco.jpg\" width=\"516\"/>\n</div>\n<div class=\"entry-content\">\n <div id=\"fb-root\">\n </div>\n <p class=\"has-small-font-size\">\n  \u7279\u8272\u56fe\u7247\uff1a\u4f69\u5357\u5e03\u79d1\u7684\u5df4\u7f57\u00b7\u5e03\u5170\u79d1\uff08Barro Branco\uff09\u7684\u7eb5\u706b\u3002 \u8d44\u6599\u6765\u6e90\uff1a\u65b0\u6c11\u4e3b\u56fd\u5bb6\u3002\n </p>\n <p>\n  \u4e00\u4f4d\u65b0\u6c11\u4e3b\u515a\uff08\u53ca\u5176\uff09\u62a5\u544a\u4e86\u5bf9\u4f69\u5357\u5e03\u79d1\u5df4\u7f57\u00b7\u5e03\u5170\u79d1\uff08Barro Branco\uff09\u7684\u519c\u6c11\u7684\u65b0\u5211\u4e8b\u88ad\u51fb\uff0c\u540e\u8005\u66fe\u4ee5\u82f1\u52c7\u7684latifundium\u7684\u88ad\u51fb\uff0c\u5e76\u64a4\u9000\u4e86\u5176\u201cInvas\u00e3oZero\u201d Goons\u3002\n </p>\n <figure class=\"wp-block-embed is-type-wp-embed is-provider-a-nova-democracia wp-block-embed-a-nova-democracia\">\n  <div class=\"wp-block-embed__wrapper\">\n   <blockquote class=\"wp-embedded-content\" data-secret=\"XlIlmVxKhs\">\n    <a href=\"https://anovademocracia.com.br/bando-incendeia-plantacoes-barro-branco/\">\n     PE\uff1aBarro Branco\u4e2d\u7684\u64c5\u81ea\u5360\u5730\u8005\u70b9\u71c3\u79cd\u690d\u56ed\n    </a>\n   </blockquote>\n   <iframe class=\"wp-embedded-content\" data-secret=\"XlIlmVxKhs\" frameborder=\"0\" height=\"338\" marginheight=\"0\" marginwidth=\"0\" sandbox=\"allow-scripts\" scrolling=\"no\" security=\"restricted\" src=\"https://anovademocracia.com.br/bando-incendeia-plantacoes-barro-branco/embed/#?secret=D1qg1ARVPd#?secret=XlIlmVxKhs\" style=\"position: absolute; visibility: hidden;\" title=\"\u201cPE: Bando incendeia planta\u00e7\u00f5es de posseiros em Barro Branco\u201d \u2014 A Nova Democracia\" width=\"600\">\n   </iframe>\n  </div>\n </figure>\n <p>\n  \u5df4\u7f57\u00b7\u5e03\u5170\u79d1\uff08Barro Branco\uff09\u5360\u9886\u8005\u6597\u4e89\u7684\u652f\u6301\u59d4\u5458\u4f1a\u53d1\u5e03\u4e86\u4e00\u7cfb\u5217\u56fe\u50cf\uff0c\u663e\u793a\u4e86\u8eab\u4efd\u4e0d\u660e\u7684\u7f6a\u72af\u9020\u6210\u7684\u51e0\u8d77\u5927\u706b\u3002\n </p>\n <p>\n  <a href=\"https://www.instagram.com/comitedeapoiobarrobranco/p/DCR2akUP4Kd/?img_index=3\">\n   https://www.instagram.com/comitedeapoiobarrobranco/p/DCR2akUP4Kd/?img_index=3\n  </a>\n </p>\n <p>\n  It was quickly understood wherefrom this criminal attack came: it was carried out by the latifundium. Its gunmen \u201cwere seen around the plantations.\u201d \u8fd9\u4e9b\u67aa\u624b\u7531\u5927\u623f\u4e1c\u516c\u53f8Agropecu\u00e1riaMataSul S.A\u9886\u5bfc\u3002\u4ed6\u4eec\u7684\u76ee\u6807\u662f\u653b\u51fb\u8be5\u5730\u533a\u7684\u7e41\u8363\u800c\u57fa\u672c\u7684\u519c\u4f5c\u7269\uff1aSugar Cane\u3002 \u4ed6\u4eec\u8fdb\u884c\u7684\u5176\u4ed6\u653b\u51fb\u662f\u6bd2\u836f\uff0c\u8bd5\u56fe\u5c06\u519c\u6c11\u9a71\u9010\u51fa\u571f\u5730\uff0c\u4f46\u4e00\u5207\u90fd\u6ca1\u6709\u6210\u529f\u3002\n </p>\n <p>\n  \u6b63\u5982\u6211\u4eec\u62a5\u9053\u7684\u90a3\u6837\uff0c\u7531\u8d2b\u7a77\u519c\u6c11\u8054\u76df\uff08LCP\uff09\u9886\u5bfc\u7684\u5df4\u7f57\u00b7\u5e03\u5170\u79d1\uff08Barro Branco\uff09\u7684\u519c\u6c11\u6b63\u5728\u6fc0\u70c8\u62b5\u6297Latifundium\u7684\u653b\u51fb\uff0c\u5e76\u5728\u5b66\u751f\u548c\u6c11\u4e3b\u77e5\u8bc6\u5206\u5b50\u7684\u652f\u6301\u4e0b\uff0c\u57289\u670828\u65e5\u5728\u5df4\u7f57\u00b7\u5e03\u5170\u79d1\uff08Barro Branco\uff09\u7684\u5149\u8363\u6218\u5f79\u4e2d \u3002\n </p>\n <figure class=\"wp-block-embed is-type-wp-embed is-provider-the-red-herald wp-block-embed-the-red-herald\">\n  <div class=\"wp-block-embed__wrapper\">\n   <blockquote class=\"wp-embedded-content\" data-secret=\"cf0uXIjZDZ\">\n    <a href=\"https://redherald.org/2024/10/24/on-the-struggle-for-land-in-barro-branco-brazil/\">\n     \u5728\u5df4\u7f57\u00b7\u5e03\u5170\u79d1\uff08Barro Branco\uff09\u7684\u571f\u5730\u4e0a\u7684\u6597\u4e89\n    </a>\n   </blockquote>\n   <iframe class=\"wp-embedded-content\" data-secret=\"cf0uXIjZDZ\" frameborder=\"0\" height=\"338\" marginheight=\"0\" marginwidth=\"0\" sandbox=\"allow-scripts\" scrolling=\"no\" security=\"restricted\" src=\"https://redherald.org/2024/10/24/on-the-struggle-for-land-in-barro-branco-brazil/embed/#?secret=K0TRLJlqft#?secret=cf0uXIjZDZ\" style=\"position: absolute; visibility: hidden;\" title=\"\u201cOn the struggle for land in Barro Branco, Brazil\u201d \u2014 The Red Herald\" width=\"600\">\n   </iframe>\n  </div>\n </figure>\n <p>\n  \u8fd9\u662f\u90a3\u4e9b\u4e0d\u4ec5\u8981\u6218\u6597\u548c\u62b5\u6297\uff0c\u800c\u4e14\u51fb\u8d25latifundium\uff0c\u4f7f\u5176\u64a4\u9000\u5e76\u9003\u8dd1\u7684\u4eba\u8981\u4ed8\u51fa\u7684\u4ee3\u4ef7\u3002 \u4f46\u662f\uff0c\u6b63\u5982\u519c\u6c11\u62a5\u9053\u5e76\u62a5\u9053\u67aa\u624b\u7684\u90a3\u6837\uff1a\u201c\u4ed6\u4eec\u5c06\u4e0d\u4f1a\u6210\u529f\u5730\u5413barro Branco\u7684\u5360\u9886\u8005\uff0c\u5df4\u7f57\u00b7\u5e03\u5170\u79d1\uff08Barro Branco\uff09\u5c06\u5728\u591c\u95f4\u548c\u767d\u5929\u6323\u624e\uff0c\u4ee5\u83b7\u53d6\u6b63\u786e\u5c5e\u4e8e\u4ed6\u4eec\u7684\u571f\u5730\uff01\u201d\n </p>\n</div>", "pdf_content": "", "pdf_links": [], "source": "https://redherald.org/2024/11/14/new-attack-by-the-latifundium-on-the-peasants-of-barro-branco/", "type": "article", "title": "Latifundium\u5bf9Barro Branco\u519c\u6c11\u7684\u65b0\u653b\u51fb - \u7ea2\u8272\u5148\u9a71", "description": "\u8bfa\u74e6\u6c11\u4e3b\u515a\uff08Nova Democracia\uff09\uff08\u53ca\u5176\u6628\u5929\uff09\u62a5\u544a\u4e86\u9488\u5bf9\u4f69\u5357\u5e03\u79d1\uff08Pernambuco\uff09\u5df4\u7f57\u00b7\u5e03\u5170\u79d1\uff08Barro Branco\uff09\u7684\u519c\u6c11\u7684\u65b0\u5211\u4e8b\u88ad\u51fb\uff0c\u4ed6\u62d2\u7edd\u4e86latifundium\u82f1\u96c4\u5730\u88ad\u51fb\uff0c\u5e76\u64a4\u9000\u4e86\u5176\u201cInvas\u00e3oZoZero\u201d\u3002", "modified time": "2024-11-14T20:49:31+00:00", "author": ["G.D."], "categories": ["Featured", "The Americas"], "tags": ["Brazil", "Repression", "Struggle for land"], "sections": ["Featured", "The Americas", "Brazil", "Repression", "Struggle for land", "English"], "source_name": "Red Herald"}